tiafork/__init__.py
tiafork/analysis/__init__.py
tiafork/analysis/pdf_rpts.py
tiafork/analysis/perf.py
tiafork/analysis/plots.py
tiafork/analysis/ta.py
tiafork/analysis/talib_wrapper.py
tiafork/analysis/util.py
tiafork/analysis/model/__init__.py
tiafork/analysis/model/ins.py
tiafork/analysis/model/interface.py
tiafork/analysis/model/pl.py
tiafork/analysis/model/port.py
tiafork/analysis/model/pos.py
tiafork/analysis/model/ret.py
tiafork/analysis/model/trd.py
tiafork/analysis/model/txn.py
tiafork/bbg/__init__.py
tiafork/bbg/bbg_com.py
tiafork/bbg/datamgr.py
tiafork/bbg/example.py
tiafork/bbg/v3api.py
tiafork/rlab/__init__.py
tiafork/rlab/builder.py
tiafork/rlab/components.py
tiafork/rlab/font.py
tiafork/rlab/patch.py
tiafork/rlab/sample.py
tiafork/rlab/table.py
tiafork/tests/__init__.py
tiafork/tests/test_analysis.py
tiafork/tests/test_datamgr.py
tiafork/tests/test_fmt.py
tiafork/tests/test_rlab_table.py
tiafork/tests/test_ta.py
tiafork/util/__init__.py
tiafork/util/decorator.py
tiafork/util/fmt.py
tiafork/util/log.py
tiafork/util/mplot.py
tiafork/util/windows.py
tiafork-1.2.3.dist-info/LICENSE
tiafork-1.2.3.dist-info/METADATA
tiafork-1.2.3.dist-info/WHEEL
tiafork-1.2.3.dist-info/top_level.txt
tiafork-1.2.3.dist-info/RECORD
